erbs/__init__.py
erbs/ops.py
erbs/utils.py
erbs/ase_main/__init__.py
erbs/ase_main/calculators/__init__.py
erbs/ase_main/calculators/plumed.py
erbs/bias/__init__.py
erbs/bias/energy_function_factory.py
erbs/bias/kernel.py
erbs/bias/potential.py
erbs/bias/state.py
erbs/cv/__init__.py
erbs/cv/cv_nl.py
erbs/descriptor/__init__.py
erbs/descriptor/example_descriptor.py
erbs/dim_reduction/__init__.py
erbs/dim_reduction/elementwise_pca.py
erbs/nodes/__init__.py
erbs/nodes/bias_calc.py
erbs/transformations/__init__.py
erbs/transformations/mass_repartition.py
erbs-0.2.0.dist-info/METADATA
erbs-0.2.0.dist-info/WHEEL
erbs-0.2.0.dist-info/RECORD
