Metadata-Version: 2.4
Name: erbs
Version: 0.2.0
Summary: Enhanced sampling in the representation space of atomistic neural networks.
Project-URL: Repository, https://github.com/apax-hub/erbs
Project-URL: Releases, https://github.com/apax-hub/erbs/releases
Project-URL: Discord, https://discord.gg/7ncfwhsnm4
Project-URL: Documentation, https://erbs.readthedocs.io/
Author-email: Moritz René Schäfer <schaefer@theochem.uni-stuttgart.de>
License-Expression: MIT
Keywords: enhanced sampling,interatomic potentials,machine-learning,molecular-dynamics
Requires-Python: >=3.10
Requires-Dist: apax>=0.12.0
Requires-Dist: ase>=3.24.0
Requires-Dist: jax==0.6.2
Requires-Dist: numpy>=1.23
Requires-Dist: scikit-learn>=1.6.1
Provides-Extra: cuda
Requires-Dist: jax[cuda]; extra == 'cuda'
Provides-Extra: docs
Requires-Dist: furo>=2023.9.10; extra == 'docs'
Requires-Dist: ipykernel>=6.29.3; extra == 'docs'
Requires-Dist: myst-parser>=2.0.0; extra == 'docs'
Requires-Dist: nbsphinx-link>=1.3.0; extra == 'docs'
Requires-Dist: nbsphinx>=0.9.3; extra == 'docs'
Requires-Dist: pandoc>=2.3; extra == 'docs'
Requires-Dist: sphinx-copybutton>=0.5.2; extra == 'docs'
Requires-Dist: sphinx-rtd-theme>=1.3.0; extra == 'docs'
Requires-Dist: sphinx>=7.2.6; extra == 'docs'
Provides-Extra: zntrack
Requires-Dist: zntrack>=0.8.9; extra == 'zntrack'
